{"entity":"EFLOA","period":"2024Q3","sched_t":[{"state":"CA","name":"California","life":74327952.0,"annuity":1297633255.0,"total":1371961207.0},{"state":"FL","name":"Florida","life":59013702.0,"annuity":1033680302.0,"total":1092694004.0},{"state":"TX","name":"Texas","life":54416269.0,"annuity":892971349.0,"total":947387618.0},{"state":"PA","name":"Pennsylvania","life":30999443.0,"annuity":769315244.0,"total":800314687.0},{"state":"NJ","name":"New Jersey","life":51010953.0,"annuity":518187780.0,"total":569198733.0},{"state":"IL","name":"Illinois","life":27407848.0,"annuity":449416040.0,"total":476823888.0},{"state":"OH","name":"Ohio","life":15430254.0,"annuity":454315520.0,"total":469745774.0},{"state":"MI","name":"Michigan","life":16459872.0,"annuity":428793613.0,"total":445253485.0},{"state":"NC","name":"North Carolina","life":21691884.0,"annuity":348119366.0,"total":369811250.0},{"state":"AZ","name":"Arizona","life":12178901.0,"annuity":318375515.0,"total":330554416.0},{"state":"MD","name":"Maryland","life":11268707.0,"annuity":244981584.0,"total":256250291.0},{"state":"WA","name":"Washington","life":20719579.0,"annuity":231998828.0,"total":252718407.0},{"state":"MA","name":"Massachusetts","life":14568413.0,"annuity":233712396.0,"total":248280809.0},{"state":"VA","name":"Virginia","life":18359787.0,"annuity":229078770.0,"total":247438557.0},{"state":"GA","name":"Georgia","life":19547309.0,"annuity":221103167.0,"total":240650476.0},{"state":"CO","name":"Colorado","life":16715353.0,"annuity":209533763.0,"total":226249116.0},{"state":"MN","name":"Minnesota","life":8227660.0,"annuity":217468821.0,"total":225696481.0},{"state":"WI","name":"Wisconsin","life":10145068.0,"annuity":182914416.0,"total":193059484.0},{"state":"CT","name":"Connecticut","life":9692578.0,"annuity":179419231.0,"total":189111809.0},{"state":"TN","name":"Tennessee","life":6848320.0,"annuity":173577068.0,"total":180425388.0},{"state":"IN","name":"Indiana","life":5854244.0,"annuity":174449670.0,"total":180303914.0},{"state":"LA","name":"Louisiana","life":14305432.0,"annuity":136404537.0,"total":150709969.0},{"state":"SC","name":"South Carolina","life":7403211.0,"annuity":142891545.0,"total":150294756.0},{"state":"IA","name":"Iowa","life":3081699.0,"annuity":134037341.0,"total":137119040.0},{"state":"AL","name":"Alabama","life":12213960.0,"annuity":117762946.0,"total":129976906.0},{"state":"UT","name":"Utah","life":12381307.0,"annuity":98417260.0,"total":110798567.0},{"state":"NE","name":"Nebraska","life":2366053.0,"annuity":102583441.0,"total":104949494.0},{"state":"AR","name":"Arkansas","life":3738111.0,"annuity":88849117.0,"total":92587228.0},{"state":"PR","name":"Puerto Rico","life":134379.0,"annuity":92053880.0,"total":92188259.0},{"state":"KS","name":"Kansas","life":4631643.0,"annuity":83707269.0,"total":88338912.0},{"state":"NH","name":"New Hampshire","life":982944.0,"annuity":85563607.0,"total":86546551.0},{"state":"NV","name":"Nevada","life":3971376.0,"annuity":76738502.0,"total":80709878.0},{"state":"KY","name":"Kentucky","life":4858336.0,"annuity":72744780.0,"total":77603116.0},{"state":"OK","name":"Oklahoma","life":3853943.0,"annuity":63821160.0,"total":67675103.0},{"state":"DE","name":"Delaware","life":2599650.0,"annuity":53334300.0,"total":55933950.0},{"state":"VT","name":"Vermont","life":1440809.0,"annuity":53441056.0,"total":54881865.0},{"state":"ME","name":"Maine","life":948720.0,"annuity":47785230.0,"total":48733950.0},{"state":"WV","name":"West Virginia","life":2189344.0,"annuity":43508352.0,"total":45697696.0},{"state":"MS","name":"Mississippi","life":2873508.0,"annuity":40514576.0,"total":43388084.0},{"state":"RI","name":"Rhode Island","life":751735.0,"annuity":40820200.0,"total":41571935.0},{"state":"HI","name":"Hawaii","life":2281136.0,"annuity":38454992.0,"total":40736128.0},{"state":"ID","name":"Idaho","life":2209187.0,"annuity":34901880.0,"total":37111067.0},{"state":"NM","name":"New Mexico","life":2121203.0,"annuity":30055409.0,"total":32176612.0},{"state":"ND","name":"North Dakota","life":1007346.0,"annuity":30378871.0,"total":31386217.0},{"state":"OR","name":"Oregon","life":3933705.0,"annuity":27138195.0,"total":31071900.0},{"state":"MO","name":"Missouri","life":7635145.0,"annuity":21218442.0,"total":28853587.0},{"state":"NY","name":"New York","life":5381657.0,"annuity":22407055.0,"total":27788712.0},{"state":"SD","name":"South Dakota","life":2774657.0,"annuity":21128135.0,"total":23902792.0},{"state":"WY","name":"Wyoming","life":969647.0,"annuity":15136521.0,"total":16106168.0},{"state":"MT","name":"Montana","life":926668.0,"annuity":10742208.0,"total":11668876.0},{"state":"DC","name":"District Of Columbia","life":1781655.0,"annuity":8861455.0,"total":10643110.0},{"state":"AK","name":"Alaska","life":306169.0,"annuity":7548367.0,"total":7854536.0},{"state":"VI","name":"U.S. Virgin Islands","life":26059.0,"annuity":0.0,"total":26059.0},{"state":"GU","name":"Guam","life":2846.0,"annuity":0.0,"total":2846.0}],"sched_d_quality":[{"category":"BONDS","naic":"NAIC 1","current":2036582178.0,"prior":1598806807.0},{"category":"BONDS","naic":"NAIC 2","current":1074480831.0,"prior":1070116195.0},{"category":"BONDS","naic":"NAIC 2","current":16643528.0,"prior":19133640.0}],"sched_b":{"count":95,"total_bv":384.0,"by_state":[{"state":"VA","count":3,"bv":384.0,"avg_rate":0}],"rate_histogram":[],"top_loans":[{"city":"","state":"","bv":7034.0,"rate":0.0},{"city":"","state":"","bv":7034.0,"rate":0.0},{"city":"","state":"","bv":7034.0,"rate":0.0},{"city":"170-S&P500 Life Hedge N/A Equity/Index","state":"BPA","bv":2282.0,"rate":0.0},{"city":"170-S&P500 Life Hedge N/A Equity/Index","state":"BPA","bv":2282.0,"rate":0.0},{"city":"170-S&P500 Life Hedge N/A Equity/Index","state":"BPA","bv":2282.0,"rate":0.0},{"city":"172-S&P500 Life Hedge N/A Equity/Index","state":"BBI","bv":2060.0,"rate":0.0},{"city":"172-S&P500 Life Hedge N/A Equity/Index","state":"BBI","bv":2060.0,"rate":0.0},{"city":"172-S&P500 Life Hedge N/A Equity/Index","state":"BBI","bv":2060.0,"rate":0.0},{"city":"","state":"","bv":1886.0,"rate":0.0},{"city":"","state":"","bv":1886.0,"rate":0.0},{"city":"","state":"","bv":1886.0,"rate":0.0},{"city":"168-S&P500 Life Hedge N/A Equity/Index","state":"BBI","bv":1417.0,"rate":0.0},{"city":"168-S&P500 Life Hedge N/A Equity/Index","state":"BBI","bv":1417.0,"rate":0.0},{"city":"168-S&P500 Life Hedge N/A Equity/Index","state":"BBI","bv":1417.0,"rate":0.0},{"city":"175-S&P500 Life Hedge N/A Equity/Index","state":"BBI","bv":1382.0,"rate":0.0},{"city":"175-S&P500 Life Hedge N/A Equity/Index","state":"BBI","bv":1382.0,"rate":0.0},{"city":"175-S&P500 Life Hedge N/A Equity/Index","state":"BBI","bv":1382.0,"rate":0.0},{"city":"180-S&P500 Life Hedge N/A Equity/Index","state":"WFC","bv":1243.0,"rate":0.0},{"city":"180-S&P500 Life Hedge N/A Equity/Index","state":"WFC","bv":1243.0,"rate":0.0},{"city":"180-S&P500 Life Hedge N/A Equity/Index","state":"WFC","bv":1243.0,"rate":0.0},{"city":"169-S&P500 Life Hedge N/A Equity/Index","state":"BPA","bv":1128.0,"rate":0.0},{"city":"169-S&P500 Life Hedge N/A Equity/Index","state":"BPA","bv":1128.0,"rate":0.0},{"city":"169-S&P500 Life Hedge N/A Equity/Index","state":"BPA","bv":1128.0,"rate":0.0},{"city":"186-S&P500 Life Hedge N/A Equity/Index","state":"WFC","bv":1100.0,"rate":0.0},{"city":"186-S&P500 Life Hedge N/A Equity/Index","state":"WFC","bv":1100.0,"rate":0.0},{"city":"186-S&P500 Life Hedge N/A Equity/Index","state":"WFC","bv":1100.0,"rate":0.0},{"city":"","state":"","bv":1056.0,"rate":0.0},{"city":"","state":"","bv":1056.0,"rate":0.0},{"city":"","state":"","bv":1056.0,"rate":0.0},{"city":"189-S&P500 Life Hedge N/A Equity/Index","state":"WFC","bv":915.0,"rate":0.0},{"city":"189-S&P500 Life Hedge N/A Equity/Index","state":"WFC","bv":915.0,"rate":0.0},{"city":"189-S&P500 Life Hedge N/A Equity/Index","state":"WFC","bv":915.0,"rate":0.0},{"city":"192-S&P500 Life Hedge N/A Equity/Index","state":"BOA","bv":867.0,"rate":0.0},{"city":"192-S&P500 Life Hedge N/A Equity/Index","state":"BOA","bv":867.0,"rate":0.0},{"city":"192-S&P500 Life Hedge N/A Equity/Index","state":"BOA","bv":867.0,"rate":0.0},{"city":"188-S&P500 Life Hedge N/A Equity/Index","state":"BBI","bv":844.0,"rate":0.0},{"city":"188-S&P500 Life Hedge N/A Equity/Index","state":"BBI","bv":844.0,"rate":0.0},{"city":"188-S&P500 Life Hedge N/A Equity/Index","state":"BBI","bv":844.0,"rate":0.0},{"city":"","state":"","bv":804.0,"rate":0.0},{"city":"","state":"","bv":804.0,"rate":0.0},{"city":"","state":"","bv":804.0,"rate":0.0},{"city":"193-S&P500 Life Hedge N/A Equity/Index","state":"BOA","bv":250.0,"rate":0.0},{"city":"193-S&P500 Life Hedge N/A Equity/Index","state":"BOA","bv":250.0,"rate":0.0},{"city":"193-S&P500 Life Hedge N/A Equity/Index","state":"BOA","bv":250.0,"rate":0.0},{"city":"173-S&P500 Life Hedge N/A Equity/Index","state":"BBI","bv":232.0,"rate":0.0},{"city":"173-S&P500 Life Hedge N/A Equity/Index","state":"BBI","bv":232.0,"rate":0.0},{"city":"173-S&P500 Life Hedge N/A Equity/Index","state":"BBI","bv":232.0,"rate":0.0},{"city":"","state":"","bv":228.0,"rate":0.0},{"city":"","state":"","bv":228.0,"rate":0.0}]},"sched_ba":{"count":172,"total_bv":0.0,"top":[]}}