{"entity":"NELIC","period":"2023Q1","sched_t":[{"state":"NY","name":"New York","life":3475605.0,"annuity":121112.0,"total":3596717.0},{"state":"PA","name":"Pennsylvania","life":2699675.0,"annuity":28500.0,"total":2728175.0},{"state":"MA","name":"Massachusetts","life":2343061.0,"annuity":112033.0,"total":2455094.0},{"state":"CA","name":"California","life":2276267.0,"annuity":51626.0,"total":2327893.0},{"state":"FL","name":"Florida","life":2191812.0,"annuity":78620.0,"total":2270432.0},{"state":"NJ","name":"New Jersey","life":1856019.0,"annuity":244006.0,"total":2100025.0},{"state":"TX","name":"Texas","life":1991692.0,"annuity":18038.0,"total":2009730.0},{"state":"IL","name":"Illinois","life":1395508.0,"annuity":110363.0,"total":1505871.0},{"state":"OH","name":"Ohio","life":1272489.0,"annuity":148217.0,"total":1420706.0},{"state":"MN","name":"Minnesota","life":1189192.0,"annuity":5750.0,"total":1194942.0},{"state":"CO","name":"Colorado","life":1004516.0,"annuity":32022.0,"total":1036538.0},{"state":"SC","name":"South Carolina","life":668150.0,"annuity":7349.0,"total":675499.0},{"state":"GA","name":"Georgia","life":630591.0,"annuity":6948.0,"total":637539.0},{"state":"KS","name":"Kansas","life":626104.0,"annuity":1545.0,"total":627649.0},{"state":"CT","name":"Connecticut","life":599685.0,"annuity":7275.0,"total":606960.0},{"state":"TN","name":"Tennessee","life":591034.0,"annuity":13825.0,"total":604859.0},{"state":"MI","name":"Michigan","life":566684.0,"annuity":32703.0,"total":599387.0},{"state":"AZ","name":"Arizona","life":541196.0,"annuity":2998.0,"total":544194.0},{"state":"NC","name":"North Carolina","life":502159.0,"annuity":17171.0,"total":519330.0},{"state":"AL","name":"Alabama","life":481155.0,"annuity":3700.0,"total":484855.0},{"state":"WI","name":"Wisconsin","life":425449.0,"annuity":40000.0,"total":465449.0},{"state":"VA","name":"Virginia","life":449859.0,"annuity":2425.0,"total":452284.0},{"state":"MD","name":"Maryland","life":445940.0,"annuity":2150.0,"total":448090.0},{"state":"MO","name":"Missouri","life":442759.0,"annuity":2550.0,"total":445309.0},{"state":"DE","name":"Delaware","life":427381.0,"annuity":14500.0,"total":441881.0},{"state":"IA","name":"Iowa","life":317844.0,"annuity":0.0,"total":317844.0},{"state":"NH","name":"New Hampshire","life":285903.0,"annuity":18158.0,"total":304061.0},{"state":"LA","name":"Louisiana","life":268658.0,"annuity":3200.0,"total":271858.0},{"state":"NE","name":"Nebraska","life":267218.0,"annuity":450.0,"total":267668.0},{"state":"WV","name":"West Virginia","life":231457.0,"annuity":9300.0,"total":240757.0},{"state":"OK","name":"Oklahoma","life":237751.0,"annuity":1050.0,"total":238801.0},{"state":"WA","name":"Washington","life":222464.0,"annuity":300.0,"total":222764.0},{"state":"IN","name":"Indiana","life":208873.0,"annuity":3187.0,"total":212060.0},{"state":"MS","name":"Mississippi","life":182087.0,"annuity":15492.0,"total":197579.0},{"state":"UT","name":"Utah","life":189649.0,"annuity":300.0,"total":189949.0},{"state":"HI","name":"Hawaii","life":183598.0,"annuity":2550.0,"total":186148.0},{"state":"RI","name":"Rhode Island","life":172471.0,"annuity":4050.0,"total":176521.0},{"state":"VT","name":"Vermont","life":175646.0,"annuity":300.0,"total":175946.0},{"state":"NM","name":"New Mexico","life":171330.0,"annuity":450.0,"total":171780.0},{"state":"OR","name":"Oregon","life":154704.0,"annuity":11844.0,"total":166548.0},{"state":"ME","name":"Maine","life":154960.0,"annuity":3014.0,"total":157974.0},{"state":"NV","name":"Nevada","life":91016.0,"annuity":2397.0,"total":93413.0},{"state":"KY","name":"Kentucky","life":85837.0,"annuity":0.0,"total":85837.0},{"state":"ID","name":"Idaho","life":62159.0,"annuity":0.0,"total":62159.0},{"state":"DC","name":"District Of Columbia","life":53669.0,"annuity":0.0,"total":53669.0},{"state":"AR","name":"Arkansas","life":48370.0,"annuity":0.0,"total":48370.0},{"state":"MT","name":"Montana","life":26369.0,"annuity":600.0,"total":26969.0},{"state":"WY","name":"Wyoming","life":22067.0,"annuity":0.0,"total":22067.0},{"state":"SD","name":"South Dakota","life":13319.0,"annuity":1500.0,"total":14819.0},{"state":"ND","name":"North Dakota","life":8021.0,"annuity":0.0,"total":8021.0},{"state":"PR","name":"Puerto Rico","life":6202.0,"annuity":0.0,"total":6202.0},{"state":"AK","name":"Alaska","life":5837.0,"annuity":0.0,"total":5837.0},{"state":"GU","name":"Guam","life":613.0,"annuity":0.0,"total":613.0},{"state":"VI","name":"U.S. Virgin Islands","life":166.0,"annuity":0.0,"total":166.0}],"sched_d_quality":[],"sched_b":{"count":2,"total_bv":22999467.0,"by_state":[{"state":"TX","count":1,"bv":22999467.0,"avg_rate":0}],"rate_histogram":[],"top_loans":[{"city":"The Woodlands","state":"TX","bv":22999467.0,"rate":0.0},{"city":"","state":"","bv":6479941.0,"rate":0.0}]},"sched_ba":{"count":1,"total_bv":0.0,"top":[]}}